Metadata-Version: 2.1
Name: odoo13-addon-hr-employee-partner-external
Version: 13.0.1.0.1.dev5
Summary: Associate an external Partner to Employee
Home-page: https://github.com/OCA/hr
Author: Stefano Consolaro Associazione PNLUG - Gruppo Odoo, Odoo Community Association (OCA)
Author-email: support@odoo-community.org
License: AGPL-3
Platform: UNKNOWN
Classifier: Programming Language :: Python
Classifier: Framework :: Odoo
Classifier: Framework :: Odoo :: 13.0
Classifier: License :: OSI Approved :: GNU Affero General Public License v3
Requires-Python: >=3.5
Requires-Dist: odoo <13.1dev,>=13.0a
